{"calendar":{"20190401":{"Adults 1":{"21123":{"name":"Excellence Club Honeymoon Suite Two-Story Rooftop Terrace W\/ Plunge Pool","price":{"US":0,"CA":0,"RW":0}},"21125":{"name":"Excellence Club Imperial Suite Two-Story Rooftop Terrace W\/ Plunge Pool","price":{"US":706,"CA":592,"RW":570}},"100933":{"name":"Junior Suite Spa or Pool View","price":{"US":432,"CA":362,"RW":348}},"100935":{"name":"Junior Swim Up Suite Spa or Pool View","price":{"US":451,"CA":378,"RW":363}},"100937":{"name":"Two Story Rooftop Terrace Suite Spa or Pool View ","price":{"US":486,"CA":408,"RW":392}},"100940":{"name":"Excellence Club Junior Suite Ocean View","price":{"US":499,"CA":418,"RW":401}},"100944":{"name":"Excellence Club Two Story Rooftop Terrace Suite Ocean Front ","price":{"US":557,"CA":467,"RW":449}},"100946":{"name":"Excellence Club Honeymoon Suite W\/Private Pool","price":{"US":0,"CA":0,"RW":0}},"100948":{"name":"Excellence Club Imperial Suite W\/Private Pool","price":{"US":706,"CA":592,"RW":570}},"395416":{"name":"Excellence Club Junior Swim Up Suite Pool View","price":{"US":499,"CA":418,"RW":401}},"496624":{"name":"Excellence Club Junior Suite Pool View","price":{"US":467,"CA":391,"RW":376}},"568940":{"name":"Terrace Suite with Plunge Pool  ","price":{"US":478,"CA":401,"RW":386}}},"Adults 2":{"21123":{"name":"Excellence Club Honeymoon Suite Two-Story Rooftop Terrace W\/ Plunge Pool","price":{"US":0,"CA":0,"RW":0}},"21125":{"name":"Excellence Club Imperial Suite Two-Story Rooftop Terrace W\/ Plunge Pool","price":{"US":1146,"CA":962,"RW":924}},"100933":{"name":"Junior Suite Spa or Pool View","price":{"US":598,"CA":502,"RW":482}},"100935":{"name":"Junior Swim Up Suite Spa or Pool View","price":{"US":636,"CA":534,"RW":512}},"100937":{"name":"Two Story Rooftop Terrace Suite Spa or Pool View ","price":{"US":706,"CA":592,"RW":570}},"100940":{"name":"Excellence Club Junior Suite Ocean View","price":{"US":730,"CA":612,"RW":588}},"100944":{"name":"Excellence Club Two Story Rooftop Terrace Suite Ocean Front ","price":{"US":848,"CA":712,"RW":684}},"100946":{"name":"Excellence Club Honeymoon Suite W\/Private Pool","price":{"US":0,"CA":0,"RW":0}},"100948":{"name":"Excellence Club Imperial Suite W\/Private Pool","price":{"US":1146,"CA":962,"RW":924}},"395416":{"name":"Excellence Club Junior Swim Up Suite Pool View","price":{"US":730,"CA":612,"RW":588}},"496624":{"name":"Excellence Club Junior Suite Pool View","price":{"US":666,"CA":560,"RW":536}},"568940":{"name":"Terrace Suite with Plunge Pool  ","price":{"US":692,"CA":580,"RW":556}}},"Adults 3":{"100933":{"name":"Junior Suite Spa or Pool View","price":{"US":852,"CA":714,"RW":684}}}},"20190402":{"Adults 1":{"21123":{"name":"Excellence Club Honeymoon Suite Two-Story Rooftop Terrace W\/ Plunge Pool","price":{"US":0,"CA":0,"RW":0}},"21125":{"name":"Excellence Club Imperial Suite Two-Story Rooftop Terrace W\/ Plunge Pool","price":{"US":706,"CA":592,"RW":570}},"100933":{"name":"Junior Suite Spa or Pool View","price":{"US":432,"CA":362,"RW":348}},"100935":{"name":"Junior Swim Up Suite Spa or Pool View","price":{"US":451,"CA":378,"RW":363}},"100937":{"name":"Two Story Rooftop Terrace Suite Spa or Pool View ","price":{"US":486,"CA":408,"RW":392}},"100940":{"name":"Excellence Club Junior Suite Ocean View","price":{"US":499,"CA":418,"RW":401}},"100944":{"name":"Excellence Club Two Story Rooftop Terrace Suite Ocean Front ","price":{"US":557,"CA":467,"RW":449}},"100946":{"name":"Excellence Club Honeymoon Suite W\/Private Pool","price":{"US":0,"CA":0,"RW":0}},"100948":{"name":"Excellence Club Imperial Suite W\/Private Pool","price":{"US":706,"CA":592,"RW":570}},"395416":{"name":"Excellence Club Junior Swim Up Suite Pool View","price":{"US":499,"CA":418,"RW":401}},"496624":{"name":"Excellence Club Junior Suite Pool View","price":{"US":467,"CA":391,"RW":376}},"568940":{"name":"Terrace Suite with Plunge Pool  ","price":{"US":478,"CA":401,"RW":386}}},"Adults 2":{"21123":{"name":"Excellence Club Honeymoon Suite Two-Story Rooftop Terrace W\/ Plunge Pool","price":{"US":0,"CA":0,"RW":0}},"21125":{"name":"Excellence Club Imperial Suite Two-Story Rooftop Terrace W\/ Plunge Pool","price":{"US":1146,"CA":962,"RW":924}},"100933":{"name":"Junior Suite Spa or Pool View","price":{"US":598,"CA":502,"RW":482}},"100935":{"name":"Junior Swim Up Suite Spa or Pool View","price":{"US":636,"CA":534,"RW":512}},"100937":{"name":"Two Story Rooftop Terrace Suite Spa or Pool View ","price":{"US":706,"CA":592,"RW":570}},"100940":{"name":"Excellence Club Junior Suite Ocean View","price":{"US":730,"CA":612,"RW":588}},"100944":{"name":"Excellence Club Two Story Rooftop Terrace Suite Ocean Front ","price":{"US":848,"CA":712,"RW":684}},"100946":{"name":"Excellence Club Honeymoon Suite W\/Private Pool","price":{"US":0,"CA":0,"RW":0}},"100948":{"name":"Excellence Club Imperial Suite W\/Private Pool","price":{"US":1146,"CA":962,"RW":924}},"395416":{"name":"Excellence Club Junior Swim Up Suite Pool View","price":{"US":730,"CA":612,"RW":588}},"496624":{"name":"Excellence Club Junior Suite Pool View","price":{"US":666,"CA":560,"RW":536}},"568940":{"name":"Terrace Suite with Plunge Pool  ","price":{"US":692,"CA":580,"RW":556}}},"Adults 3":{"100933":{"name":"Junior Suite Spa or Pool View","price":{"US":852,"CA":714,"RW":684}}}},"20190403":{"Adults 1":{"21123":{"name":"Excellence Club Honeymoon Suite Two-Story Rooftop Terrace W\/ Plunge Pool","price":{"US":0,"CA":0,"RW":0}},"21125":{"name":"Excellence Club Imperial Suite Two-Story Rooftop Terrace W\/ Plunge Pool","price":{"US":0,"CA":0,"RW":0}},"100933":{"name":"Junior Suite Spa or Pool View","price":{"US":432,"CA":362,"RW":348}},"100935":{"name":"Junior Swim Up Suite Spa or Pool View","price":{"US":451,"CA":378,"RW":363}},"100937":{"name":"Two Story Rooftop Terrace Suite Spa or Pool View ","price":{"US":486,"CA":408,"RW":392}},"100940":{"name":"Excellence Club Junior Suite Ocean View","price":{"US":0,"CA":0,"RW":0}},"100944":{"name":"Excellence Club Two Story Rooftop Terrace Suite Ocean Front ","price":{"US":557,"CA":467,"RW":449}},"100946":{"name":"Excellence Club Honeymoon Suite W\/Private Pool","price":{"US":0,"CA":0,"RW":0}},"100948":{"name":"Excellence Club Imperial Suite W\/Private Pool","price":{"US":0,"CA":0,"RW":0}},"395416":{"name":"Excellence Club Junior Swim Up Suite Pool View","price":{"US":499,"CA":418,"RW":401}},"496624":{"name":"Excellence Club Junior Suite Pool View","price":{"US":467,"CA":391,"RW":376}},"568940":{"name":"Terrace Suite with Plunge Pool  ","price":{"US":0,"CA":0,"RW":0}}},"Adults 2":{"21123":{"name":"Excellence Club Honeymoon Suite Two-Story Rooftop Terrace W\/ Plunge Pool","price":{"US":0,"CA":0,"RW":0}},"21125":{"name":"Excellence Club Imperial Suite Two-Story Rooftop Terrace W\/ Plunge Pool","price":{"US":0,"CA":0,"RW":0}},"100933":{"name":"Junior Suite Spa or Pool View","price":{"US":598,"CA":502,"RW":482}},"100935":{"name":"Junior Swim Up Suite Spa or Pool View","price":{"US":636,"CA":534,"RW":512}},"100937":{"name":"Two Story Rooftop Terrace Suite Spa or Pool View ","price":{"US":706,"CA":592,"RW":570}},"100940":{"name":"Excellence Club Junior Suite Ocean View","price":{"US":0,"CA":0,"RW":0}},"100944":{"name":"Excellence Club Two Story Rooftop Terrace Suite Ocean Front ","price":{"US":848,"CA":712,"RW":684}},"100946":{"name":"Excellence Club Honeymoon Suite W\/Private Pool","price":{"US":0,"CA":0,"RW":0}},"100948":{"name":"Excellence Club Imperial Suite W\/Private Pool","price":{"US":0,"CA":0,"RW":0}},"395416":{"name":"Excellence Club Junior Swim Up Suite Pool View","price":{"US":730,"CA":612,"RW":588}},"496624":{"name":"Excellence Club Junior Suite Pool View","price":{"US":666,"CA":560,"RW":536}},"568940":{"name":"Terrace Suite with Plunge Pool  ","price":{"US":0,"CA":0,"RW":0}}},"Adults 3":{"100933":{"name":"Junior Suite Spa or Pool View","price":{"US":852,"CA":714,"RW":684}}}},"20190404":{"Adults 1":{"21123":{"name":"Excellence Club Honeymoon Suite Two-Story Rooftop Terrace W\/ Plunge Pool","price":{"US":0,"CA":0,"RW":0}},"21125":{"name":"Excellence Club Imperial Suite Two-Story Rooftop Terrace W\/ Plunge Pool","price":{"US":0,"CA":0,"RW":0}},"100933":{"name":"Junior Suite Spa or Pool View","price":{"US":432,"CA":362,"RW":432}},"100935":{"name":"Junior Swim Up Suite Spa or Pool View","price":{"US":0,"CA":0,"RW":0}},"100937":{"name":"Two Story Rooftop Terrace Suite Spa or Pool View ","price":{"US":486,"CA":408,"RW":392}},"100940":{"name":"Excellence Club Junior Suite Ocean View","price":{"US":0,"CA":0,"RW":0}},"100944":{"name":"Excellence Club Two Story Rooftop Terrace Suite Ocean Front ","price":{"US":0,"CA":0,"RW":0}},"100946":{"name":"Excellence Club Honeymoon Suite W\/Private Pool","price":{"US":0,"CA":0,"RW":0}},"100948":{"name":"Excellence Club Imperial Suite W\/Private Pool","price":{"US":0,"CA":0,"RW":0}},"395416":{"name":"Excellence Club Junior Swim Up Suite Pool View","price":{"US":0,"CA":0,"RW":0}},"496624":{"name":"Excellence Club Junior Suite Pool View","price":{"US":0,"CA":0,"RW":0}},"568940":{"name":"Terrace Suite with Plunge Pool  ","price":{"US":0,"CA":0,"RW":0}}},"Adults 2":{"21123":{"name":"Excellence Club Honeymoon Suite Two-Story Rooftop Terrace W\/ Plunge Pool","price":{"US":0,"CA":0,"RW":0}},"21125":{"name":"Excellence Club Imperial Suite Two-Story Rooftop Terrace W\/ Plunge Pool","price":{"US":0,"CA":0,"RW":0}},"100933":{"name":"Junior Suite Spa or Pool View","price":{"US":598,"CA":502,"RW":598}},"100935":{"name":"Junior Swim Up Suite Spa or Pool View","price":{"US":0,"CA":0,"RW":0}},"100937":{"name":"Two Story Rooftop Terrace Suite Spa or Pool View ","price":{"US":706,"CA":592,"RW":570}},"100940":{"name":"Excellence Club Junior Suite Ocean View","price":{"US":0,"CA":0,"RW":0}},"100944":{"name":"Excellence Club Two Story Rooftop Terrace Suite Ocean Front ","price":{"US":0,"CA":0,"RW":0}},"100946":{"name":"Excellence Club Honeymoon Suite W\/Private Pool","price":{"US":0,"CA":0,"RW":0}},"100948":{"name":"Excellence Club Imperial Suite W\/Private Pool","price":{"US":0,"CA":0,"RW":0}},"395416":{"name":"Excellence Club Junior Swim Up Suite Pool View","price":{"US":0,"CA":0,"RW":0}},"496624":{"name":"Excellence Club Junior Suite Pool View","price":{"US":0,"CA":0,"RW":0}},"568940":{"name":"Terrace Suite with Plunge Pool  ","price":{"US":0,"CA":0,"RW":0}}},"Adults 3":{"100933":{"name":"Junior Suite Spa or Pool View","price":{"US":852,"CA":714,"RW":852}}}},"20190405":{"Adults 1":{"21123":{"name":"Excellence Club Honeymoon Suite Two-Story Rooftop Terrace W\/ Plunge Pool","price":{"US":0,"CA":0,"RW":0}},"21125":{"name":"Excellence Club Imperial Suite Two-Story Rooftop Terrace W\/ Plunge Pool","price":{"US":0,"CA":0,"RW":0}},"100933":{"name":"Junior Suite Spa or Pool View","price":{"US":432,"CA":362,"RW":432}},"100935":{"name":"Junior Swim Up Suite Spa or Pool View","price":{"US":0,"CA":0,"RW":0}},"100937":{"name":"Two Story Rooftop Terrace Suite Spa or Pool View ","price":{"US":486,"CA":408,"RW":392}},"100940":{"name":"Excellence Club Junior Suite Ocean View","price":{"US":0,"CA":0,"RW":0}},"100944":{"name":"Excellence Club Two Story Rooftop Terrace Suite Ocean Front ","price":{"US":0,"CA":0,"RW":0}},"100946":{"name":"Excellence Club Honeymoon Suite W\/Private Pool","price":{"US":643,"CA":539,"RW":519}},"100948":{"name":"Excellence Club Imperial Suite W\/Private Pool","price":{"US":0,"CA":0,"RW":0}},"395416":{"name":"Excellence Club Junior Swim Up Suite Pool View","price":{"US":499,"CA":418,"RW":401}},"496624":{"name":"Excellence Club Junior Suite Pool View","price":{"US":0,"CA":0,"RW":0}},"568940":{"name":"Terrace Suite with Plunge Pool  ","price":{"US":478,"CA":401,"RW":386}}},"Adults 2":{"21123":{"name":"Excellence Club Honeymoon Suite Two-Story Rooftop Terrace W\/ Plunge Pool","price":{"US":0,"CA":0,"RW":0}},"21125":{"name":"Excellence Club Imperial Suite Two-Story Rooftop Terrace W\/ Plunge Pool","price":{"US":0,"CA":0,"RW":0}},"100933":{"name":"Junior Suite Spa or Pool View","price":{"US":598,"CA":502,"RW":598}},"100935":{"name":"Junior Swim Up Suite Spa or Pool View","price":{"US":0,"CA":0,"RW":0}},"100937":{"name":"Two Story Rooftop Terrace Suite Spa or Pool View ","price":{"US":706,"CA":592,"RW":570}},"100940":{"name":"Excellence Club Junior Suite Ocean View","price":{"US":0,"CA":0,"RW":0}},"100944":{"name":"Excellence Club Two Story Rooftop Terrace Suite Ocean Front ","price":{"US":0,"CA":0,"RW":0}},"100946":{"name":"Excellence Club Honeymoon Suite W\/Private Pool","price":{"US":1020,"CA":856,"RW":822}},"100948":{"name":"Excellence Club Imperial Suite W\/Private Pool","price":{"US":0,"CA":0,"RW":0}},"395416":{"name":"Excellence Club Junior Swim Up Suite Pool View","price":{"US":730,"CA":612,"RW":588}},"496624":{"name":"Excellence Club Junior Suite Pool View","price":{"US":0,"CA":0,"RW":0}},"568940":{"name":"Terrace Suite with Plunge Pool  ","price":{"US":692,"CA":580,"RW":556}}},"Adults 3":{"100933":{"name":"Junior Suite Spa or Pool View","price":{"US":852,"CA":714,"RW":852}}}},"20190406":{"Adults 1":{"21123":{"name":"Excellence Club Honeymoon Suite Two-Story Rooftop Terrace W\/ Plunge Pool","price":{"US":0,"CA":0,"RW":0}},"21125":{"name":"Excellence Club Imperial Suite Two-Story Rooftop Terrace W\/ Plunge Pool","price":{"US":0,"CA":0,"RW":0}},"100933":{"name":"Junior Suite Spa or Pool View","price":{"US":432,"CA":362,"RW":432}},"100935":{"name":"Junior Swim Up Suite Spa or Pool View","price":{"US":451,"CA":378,"RW":451}},"100937":{"name":"Two Story Rooftop Terrace Suite Spa or Pool View ","price":{"US":486,"CA":408,"RW":392}},"100940":{"name":"Excellence Club Junior Suite Ocean View","price":{"US":499,"CA":418,"RW":401}},"100944":{"name":"Excellence Club Two Story Rooftop Terrace Suite Ocean Front ","price":{"US":0,"CA":0,"RW":0}},"100946":{"name":"Excellence Club Honeymoon Suite W\/Private Pool","price":{"US":0,"CA":0,"RW":0}},"100948":{"name":"Excellence Club Imperial Suite W\/Private Pool","price":{"US":0,"CA":0,"RW":0}},"395416":{"name":"Excellence Club Junior Swim Up Suite Pool View","price":{"US":0,"CA":0,"RW":0}},"496624":{"name":"Excellence Club Junior Suite Pool View","price":{"US":0,"CA":0,"RW":0}},"568940":{"name":"Terrace Suite with Plunge Pool  ","price":{"US":478,"CA":401,"RW":386}}},"Adults 2":{"21123":{"name":"Excellence Club Honeymoon Suite Two-Story Rooftop Terrace W\/ Plunge Pool","price":{"US":0,"CA":0,"RW":0}},"21125":{"name":"Excellence Club Imperial Suite Two-Story Rooftop Terrace W\/ Plunge Pool","price":{"US":0,"CA":0,"RW":0}},"100933":{"name":"Junior Suite Spa or Pool View","price":{"US":598,"CA":502,"RW":598}},"100935":{"name":"Junior Swim Up Suite Spa or Pool View","price":{"US":636,"CA":534,"RW":636}},"100937":{"name":"Two Story Rooftop Terrace Suite Spa or Pool View ","price":{"US":706,"CA":592,"RW":570}},"100940":{"name":"Excellence Club Junior Suite Ocean View","price":{"US":730,"CA":612,"RW":588}},"100944":{"name":"Excellence Club Two Story Rooftop Terrace Suite Ocean Front ","price":{"US":0,"CA":0,"RW":0}},"100946":{"name":"Excellence Club Honeymoon Suite W\/Private Pool","price":{"US":0,"CA":0,"RW":0}},"100948":{"name":"Excellence Club Imperial Suite W\/Private Pool","price":{"US":0,"CA":0,"RW":0}},"395416":{"name":"Excellence Club Junior Swim Up Suite Pool View","price":{"US":0,"CA":0,"RW":0}},"496624":{"name":"Excellence Club Junior Suite Pool View","price":{"US":0,"CA":0,"RW":0}},"568940":{"name":"Terrace Suite with Plunge Pool  ","price":{"US":692,"CA":580,"RW":556}}},"Adults 3":{"100933":{"name":"Junior Suite Spa or Pool View","price":{"US":852,"CA":714,"RW":852}}}},"20190407":{"Adults 1":{"21123":{"name":"Excellence Club Honeymoon Suite Two-Story Rooftop Terrace W\/ Plunge Pool","price":{"US":0,"CA":0,"RW":0}},"21125":{"name":"Excellence Club Imperial Suite Two-Story Rooftop Terrace W\/ Plunge Pool","price":{"US":0,"CA":0,"RW":0}},"100933":{"name":"Junior Suite Spa or Pool View","price":{"US":432,"CA":362,"RW":432}},"100935":{"name":"Junior Swim Up Suite Spa or Pool View","price":{"US":451,"CA":378,"RW":451}},"100937":{"name":"Two Story Rooftop Terrace Suite Spa or Pool View ","price":{"US":486,"CA":408,"RW":392}},"100940":{"name":"Excellence Club Junior Suite Ocean View","price":{"US":499,"CA":418,"RW":401}},"100944":{"name":"Excellence Club Two Story Rooftop Terrace Suite Ocean Front ","price":{"US":557,"CA":467,"RW":449}},"100946":{"name":"Excellence Club Honeymoon Suite W\/Private Pool","price":{"US":0,"CA":0,"RW":0}},"100948":{"name":"Excellence Club Imperial Suite W\/Private Pool","price":{"US":706,"CA":592,"RW":570}},"395416":{"name":"Excellence Club Junior Swim Up Suite Pool View","price":{"US":0,"CA":0,"RW":0}},"496624":{"name":"Excellence Club Junior Suite Pool View","price":{"US":467,"CA":391,"RW":376}},"568940":{"name":"Terrace Suite with Plunge Pool  ","price":{"US":478,"CA":401,"RW":386}}},"Adults 2":{"21123":{"name":"Excellence Club Honeymoon Suite Two-Story Rooftop Terrace W\/ Plunge Pool","price":{"US":0,"CA":0,"RW":0}},"21125":{"name":"Excellence Club Imperial Suite Two-Story Rooftop Terrace W\/ Plunge Pool","price":{"US":0,"CA":0,"RW":0}},"100933":{"name":"Junior Suite Spa or Pool View","price":{"US":598,"CA":502,"RW":598}},"100935":{"name":"Junior Swim Up Suite Spa or Pool View","price":{"US":636,"CA":534,"RW":636}},"100937":{"name":"Two Story Rooftop Terrace Suite Spa or Pool View ","price":{"US":706,"CA":592,"RW":570}},"100940":{"name":"Excellence Club Junior Suite Ocean View","price":{"US":730,"CA":612,"RW":588}},"100944":{"name":"Excellence Club Two Story Rooftop Terrace Suite Ocean Front ","price":{"US":848,"CA":712,"RW":684}},"100946":{"name":"Excellence Club Honeymoon Suite W\/Private Pool","price":{"US":0,"CA":0,"RW":0}},"100948":{"name":"Excellence Club Imperial Suite W\/Private Pool","price":{"US":1146,"CA":962,"RW":924}},"395416":{"name":"Excellence Club Junior Swim Up Suite Pool View","price":{"US":0,"CA":0,"RW":0}},"496624":{"name":"Excellence Club Junior Suite Pool View","price":{"US":666,"CA":560,"RW":536}},"568940":{"name":"Terrace Suite with Plunge Pool  ","price":{"US":692,"CA":580,"RW":556}}},"Adults 3":{"100933":{"name":"Junior Suite Spa or Pool View","price":{"US":852,"CA":714,"RW":852}}}},"20190408":{"Adults 1":{"21123":{"name":"Excellence Club Honeymoon Suite Two-Story Rooftop Terrace W\/ Plunge Pool","price":{"US":0,"CA":0,"RW":0}},"21125":{"name":"Excellence Club Imperial Suite Two-Story Rooftop Terrace W\/ Plunge Pool","price":{"US":0,"CA":0,"RW":0}},"100933":{"name":"Junior Suite Spa or Pool View","price":{"US":432,"CA":362,"RW":348}},"100935":{"name":"Junior Swim Up Suite Spa or Pool View","price":{"US":451,"CA":378,"RW":363}},"100937":{"name":"Two Story Rooftop Terrace Suite Spa or Pool View ","price":{"US":486,"CA":408,"RW":392}},"100940":{"name":"Excellence Club Junior Suite Ocean View","price":{"US":499,"CA":418,"RW":401}},"100944":{"name":"Excellence Club Two Story Rooftop Terrace Suite Ocean Front ","price":{"US":0,"CA":0,"RW":0}},"100946":{"name":"Excellence Club Honeymoon Suite W\/Private Pool","price":{"US":0,"CA":0,"RW":0}},"100948":{"name":"Excellence Club Imperial Suite W\/Private Pool","price":{"US":0,"CA":0,"RW":0}},"395416":{"name":"Excellence Club Junior Swim Up Suite Pool View","price":{"US":499,"CA":418,"RW":401}},"496624":{"name":"Excellence Club Junior Suite Pool View","price":{"US":467,"CA":391,"RW":376}},"568940":{"name":"Terrace Suite with Plunge Pool  ","price":{"US":478,"CA":401,"RW":386}}},"Adults 2":{"21123":{"name":"Excellence Club Honeymoon Suite Two-Story Rooftop Terrace W\/ Plunge Pool","price":{"US":0,"CA":0,"RW":0}},"21125":{"name":"Excellence Club Imperial Suite Two-Story Rooftop Terrace W\/ Plunge Pool","price":{"US":0,"CA":0,"RW":0}},"100933":{"name":"Junior Suite Spa or Pool View","price":{"US":598,"CA":502,"RW":482}},"100935":{"name":"Junior Swim Up Suite Spa or Pool View","price":{"US":636,"CA":534,"RW":512}},"100937":{"name":"Two Story Rooftop Terrace Suite Spa or Pool View ","price":{"US":706,"CA":592,"RW":570}},"100940":{"name":"Excellence Club Junior Suite Ocean View","price":{"US":730,"CA":612,"RW":588}},"100944":{"name":"Excellence Club Two Story Rooftop Terrace Suite Ocean Front ","price":{"US":0,"CA":0,"RW":0}},"100946":{"name":"Excellence Club Honeymoon Suite W\/Private Pool","price":{"US":0,"CA":0,"RW":0}},"100948":{"name":"Excellence Club Imperial Suite W\/Private Pool","price":{"US":0,"CA":0,"RW":0}},"395416":{"name":"Excellence Club Junior Swim Up Suite Pool View","price":{"US":730,"CA":612,"RW":588}},"496624":{"name":"Excellence Club Junior Suite Pool View","price":{"US":666,"CA":560,"RW":536}},"568940":{"name":"Terrace Suite with Plunge Pool  ","price":{"US":692,"CA":580,"RW":556}}},"Adults 3":{"100933":{"name":"Junior Suite Spa or Pool View","price":{"US":852,"CA":714,"RW":684}}}},"20190409":{"Adults 1":{"21123":{"name":"Excellence Club Honeymoon Suite Two-Story Rooftop Terrace W\/ Plunge Pool","price":{"US":0,"CA":0,"RW":0}},"21125":{"name":"Excellence Club Imperial Suite Two-Story Rooftop Terrace W\/ Plunge Pool","price":{"US":0,"CA":0,"RW":0}},"100933":{"name":"Junior Suite Spa or Pool View","price":{"US":432,"CA":362,"RW":348}},"100935":{"name":"Junior Swim Up Suite Spa or Pool View","price":{"US":451,"CA":378,"RW":363}},"100937":{"name":"Two Story Rooftop Terrace Suite Spa or Pool View ","price":{"US":486,"CA":408,"RW":392}},"100940":{"name":"Excellence Club Junior Suite Ocean View","price":{"US":499,"CA":418,"RW":401}},"100944":{"name":"Excellence Club Two Story Rooftop Terrace Suite Ocean Front ","price":{"US":557,"CA":467,"RW":449}},"100946":{"name":"Excellence Club Honeymoon Suite W\/Private Pool","price":{"US":0,"CA":0,"RW":0}},"100948":{"name":"Excellence Club Imperial Suite W\/Private Pool","price":{"US":0,"CA":0,"RW":0}},"395416":{"name":"Excellence Club Junior Swim Up Suite Pool View","price":{"US":499,"CA":418,"RW":401}},"496624":{"name":"Excellence Club Junior Suite Pool View","price":{"US":467,"CA":391,"RW":376}},"568940":{"name":"Terrace Suite with Plunge Pool  ","price":{"US":478,"CA":401,"RW":386}}},"Adults 2":{"21123":{"name":"Excellence Club Honeymoon Suite Two-Story Rooftop Terrace W\/ Plunge Pool","price":{"US":0,"CA":0,"RW":0}},"21125":{"name":"Excellence Club Imperial Suite Two-Story Rooftop Terrace W\/ Plunge Pool","price":{"US":0,"CA":0,"RW":0}},"100933":{"name":"Junior Suite Spa or Pool View","price":{"US":598,"CA":502,"RW":482}},"100935":{"name":"Junior Swim Up Suite Spa or Pool View","price":{"US":636,"CA":534,"RW":512}},"100937":{"name":"Two Story Rooftop Terrace Suite Spa or Pool View ","price":{"US":706,"CA":592,"RW":570}},"100940":{"name":"Excellence Club Junior Suite Ocean View","price":{"US":730,"CA":612,"RW":588}},"100944":{"name":"Excellence Club Two Story Rooftop Terrace Suite Ocean Front ","price":{"US":848,"CA":712,"RW":684}},"100946":{"name":"Excellence Club Honeymoon Suite W\/Private Pool","price":{"US":0,"CA":0,"RW":0}},"100948":{"name":"Excellence Club Imperial Suite W\/Private Pool","price":{"US":0,"CA":0,"RW":0}},"395416":{"name":"Excellence Club Junior Swim Up Suite Pool View","price":{"US":730,"CA":612,"RW":588}},"496624":{"name":"Excellence Club Junior Suite Pool View","price":{"US":666,"CA":560,"RW":536}},"568940":{"name":"Terrace Suite with Plunge Pool  ","price":{"US":692,"CA":580,"RW":556}}},"Adults 3":{"100933":{"name":"Junior Suite Spa or Pool View","price":{"US":852,"CA":714,"RW":684}}}},"20190410":{"Adults 1":{"21123":{"name":"Excellence Club Honeymoon Suite Two-Story Rooftop Terrace W\/ Plunge Pool","price":{"US":0,"CA":0,"RW":0}},"21125":{"name":"Excellence Club Imperial Suite Two-Story Rooftop Terrace W\/ Plunge Pool","price":{"US":0,"CA":0,"RW":0}},"100933":{"name":"Junior Suite Spa or Pool View","price":{"US":432,"CA":362,"RW":348}},"100935":{"name":"Junior Swim Up Suite Spa or Pool View","price":{"US":451,"CA":378,"RW":363}},"100937":{"name":"Two Story Rooftop Terrace Suite Spa or Pool View ","price":{"US":486,"CA":408,"RW":392}},"100940":{"name":"Excellence Club Junior Suite Ocean View","price":{"US":499,"CA":418,"RW":401}},"100944":{"name":"Excellence Club Two Story Rooftop Terrace Suite Ocean Front ","price":{"US":557,"CA":467,"RW":449}},"100946":{"name":"Excellence Club Honeymoon Suite W\/Private Pool","price":{"US":0,"CA":0,"RW":0}},"100948":{"name":"Excellence Club Imperial Suite W\/Private Pool","price":{"US":0,"CA":0,"RW":0}},"395416":{"name":"Excellence Club Junior Swim Up Suite Pool View","price":{"US":499,"CA":418,"RW":401}},"496624":{"name":"Excellence Club Junior Suite Pool View","price":{"US":0,"CA":0,"RW":0}},"568940":{"name":"Terrace Suite with Plunge Pool  ","price":{"US":478,"CA":401,"RW":386}}},"Adults 2":{"21123":{"name":"Excellence Club Honeymoon Suite Two-Story Rooftop Terrace W\/ Plunge Pool","price":{"US":0,"CA":0,"RW":0}},"21125":{"name":"Excellence Club Imperial Suite Two-Story Rooftop Terrace W\/ Plunge Pool","price":{"US":0,"CA":0,"RW":0}},"100933":{"name":"Junior Suite Spa or Pool View","price":{"US":598,"CA":502,"RW":482}},"100935":{"name":"Junior Swim Up Suite Spa or Pool View","price":{"US":636,"CA":534,"RW":512}},"100937":{"name":"Two Story Rooftop Terrace Suite Spa or Pool View ","price":{"US":706,"CA":592,"RW":570}},"100940":{"name":"Excellence Club Junior Suite Ocean View","price":{"US":730,"CA":612,"RW":588}},"100944":{"name":"Excellence Club Two Story Rooftop Terrace Suite Ocean Front ","price":{"US":848,"CA":712,"RW":684}},"100946":{"name":"Excellence Club Honeymoon Suite W\/Private Pool","price":{"US":0,"CA":0,"RW":0}},"100948":{"name":"Excellence Club Imperial Suite W\/Private Pool","price":{"US":0,"CA":0,"RW":0}},"395416":{"name":"Excellence Club Junior Swim Up Suite Pool View","price":{"US":730,"CA":612,"RW":588}},"496624":{"name":"Excellence Club Junior Suite Pool View","price":{"US":0,"CA":0,"RW":0}},"568940":{"name":"Terrace Suite with Plunge Pool  ","price":{"US":692,"CA":580,"RW":556}}},"Adults 3":{"100933":{"name":"Junior Suite Spa or Pool View","price":{"US":852,"CA":714,"RW":684}}}},"20190411":{"Adults 1":{"21123":{"name":"Excellence Club Honeymoon Suite Two-Story Rooftop Terrace W\/ Plunge Pool","price":{"US":643,"CA":539,"RW":519}},"21125":{"name":"Excellence Club Imperial Suite Two-Story Rooftop Terrace W\/ Plunge Pool","price":{"US":0,"CA":0,"RW":0}},"100933":{"name":"Junior Suite Spa or Pool View","price":{"US":432,"CA":362,"RW":432}},"100935":{"name":"Junior Swim Up Suite Spa or Pool View","price":{"US":451,"CA":378,"RW":363}},"100937":{"name":"Two Story Rooftop Terrace Suite Spa or Pool View ","price":{"US":486,"CA":408,"RW":392}},"100940":{"name":"Excellence Club Junior Suite Ocean View","price":{"US":0,"CA":0,"RW":0}},"100944":{"name":"Excellence Club Two Story Rooftop Terrace Suite Ocean Front ","price":{"US":0,"CA":0,"RW":0}},"100946":{"name":"Excellence Club Honeymoon Suite W\/Private Pool","price":{"US":0,"CA":0,"RW":0}},"100948":{"name":"Excellence Club Imperial Suite W\/Private Pool","price":{"US":0,"CA":0,"RW":0}},"395416":{"name":"Excellence Club Junior Swim Up Suite Pool View","price":{"US":499,"CA":418,"RW":401}},"496624":{"name":"Excellence Club Junior Suite Pool View","price":{"US":467,"CA":391,"RW":376}},"568940":{"name":"Terrace Suite with Plunge Pool  ","price":{"US":478,"CA":401,"RW":386}}},"Adults 2":{"21123":{"name":"Excellence Club Honeymoon Suite Two-Story Rooftop Terrace W\/ Plunge Pool","price":{"US":1020,"CA":856,"RW":822}},"21125":{"name":"Excellence Club Imperial Suite Two-Story Rooftop Terrace W\/ Plunge Pool","price":{"US":0,"CA":0,"RW":0}},"100933":{"name":"Junior Suite Spa or Pool View","price":{"US":598,"CA":502,"RW":598}},"100935":{"name":"Junior Swim Up Suite Spa or Pool View","price":{"US":636,"CA":534,"RW":512}},"100937":{"name":"Two Story Rooftop Terrace Suite Spa or Pool View ","price":{"US":706,"CA":592,"RW":570}},"100940":{"name":"Excellence Club Junior Suite Ocean View","price":{"US":0,"CA":0,"RW":0}},"100944":{"name":"Excellence Club Two Story Rooftop Terrace Suite Ocean Front ","price":{"US":0,"CA":0,"RW":0}},"100946":{"name":"Excellence Club Honeymoon Suite W\/Private Pool","price":{"US":0,"CA":0,"RW":0}},"100948":{"name":"Excellence Club Imperial Suite W\/Private Pool","price":{"US":0,"CA":0,"RW":0}},"395416":{"name":"Excellence Club Junior Swim Up Suite Pool View","price":{"US":730,"CA":612,"RW":588}},"496624":{"name":"Excellence Club Junior Suite Pool View","price":{"US":666,"CA":560,"RW":536}},"568940":{"name":"Terrace Suite with Plunge Pool  ","price":{"US":692,"CA":580,"RW":556}}},"Adults 3":{"100933":{"name":"Junior Suite Spa or Pool View","price":{"US":852,"CA":714,"RW":852}}}},"20190412":{"Adults 1":{"21123":{"name":"Excellence Club Honeymoon Suite Two-Story Rooftop Terrace W\/ Plunge Pool","price":{"US":0,"CA":0,"RW":0}},"21125":{"name":"Excellence Club Imperial Suite Two-Story Rooftop Terrace W\/ Plunge Pool","price":{"US":706,"CA":592,"RW":570}},"100933":{"name":"Junior Suite Spa or Pool View","price":{"US":432,"CA":362,"RW":432}},"100935":{"name":"Junior Swim Up Suite Spa or Pool View","price":{"US":451,"CA":378,"RW":363}},"100937":{"name":"Two Story Rooftop Terrace Suite Spa or Pool View ","price":{"US":486,"CA":408,"RW":392}},"100940":{"name":"Excellence Club Junior Suite Ocean View","price":{"US":499,"CA":418,"RW":401}},"100944":{"name":"Excellence Club Two Story Rooftop Terrace Suite Ocean Front ","price":{"US":557,"CA":467,"RW":449}},"100946":{"name":"Excellence Club Honeymoon Suite W\/Private Pool","price":{"US":0,"CA":0,"RW":0}},"100948":{"name":"Excellence Club Imperial Suite W\/Private Pool","price":{"US":0,"CA":0,"RW":0}},"395416":{"name":"Excellence Club Junior Swim Up Suite Pool View","price":{"US":0,"CA":0,"RW":0}},"496624":{"name":"Excellence Club Junior Suite Pool View","price":{"US":467,"CA":391,"RW":376}},"568940":{"name":"Terrace Suite with Plunge Pool  ","price":{"US":478,"CA":401,"RW":386}}},"Adults 2":{"21123":{"name":"Excellence Club Honeymoon Suite Two-Story Rooftop Terrace W\/ Plunge Pool","price":{"US":0,"CA":0,"RW":0}},"21125":{"name":"Excellence Club Imperial Suite Two-Story Rooftop Terrace W\/ Plunge Pool","price":{"US":1146,"CA":962,"RW":924}},"100933":{"name":"Junior Suite Spa or Pool View","price":{"US":598,"CA":502,"RW":598}},"100935":{"name":"Junior Swim Up Suite Spa or Pool View","price":{"US":636,"CA":534,"RW":512}},"100937":{"name":"Two Story Rooftop Terrace Suite Spa or Pool View ","price":{"US":706,"CA":592,"RW":570}},"100940":{"name":"Excellence Club Junior Suite Ocean View","price":{"US":730,"CA":612,"RW":588}},"100944":{"name":"Excellence Club Two Story Rooftop Terrace Suite Ocean Front ","price":{"US":848,"CA":712,"RW":684}},"100946":{"name":"Excellence Club Honeymoon Suite W\/Private Pool","price":{"US":0,"CA":0,"RW":0}},"100948":{"name":"Excellence Club Imperial Suite W\/Private Pool","price":{"US":0,"CA":0,"RW":0}},"395416":{"name":"Excellence Club Junior Swim Up Suite Pool View","price":{"US":0,"CA":0,"RW":0}},"496624":{"name":"Excellence Club Junior Suite Pool View","price":{"US":666,"CA":560,"RW":536}},"568940":{"name":"Terrace Suite with Plunge Pool  ","price":{"US":692,"CA":580,"RW":556}}},"Adults 3":{"100933":{"name":"Junior Suite Spa or Pool View","price":{"US":852,"CA":714,"RW":852}}}},"20190413":{"Adults 1":{"21123":{"name":"Excellence Club Honeymoon Suite Two-Story Rooftop Terrace W\/ Plunge Pool","price":{"US":0,"CA":0,"RW":0}},"21125":{"name":"Excellence Club Imperial Suite Two-Story Rooftop Terrace W\/ Plunge Pool","price":{"US":706,"CA":592,"RW":570}},"100933":{"name":"Junior Suite Spa or Pool View","price":{"US":432,"CA":362,"RW":432}},"100935":{"name":"Junior Swim Up Suite Spa or Pool View","price":{"US":451,"CA":378,"RW":363}},"100937":{"name":"Two Story Rooftop Terrace Suite Spa or Pool View ","price":{"US":486,"CA":408,"RW":392}},"100940":{"name":"Excellence Club Junior Suite Ocean View","price":{"US":0,"CA":0,"RW":0}},"100944":{"name":"Excellence Club Two Story Rooftop Terrace Suite Ocean Front ","price":{"US":557,"CA":467,"RW":449}},"100946":{"name":"Excellence Club Honeymoon Suite W\/Private Pool","price":{"US":643,"CA":539,"RW":519}},"100948":{"name":"Excellence Club Imperial Suite W\/Private Pool","price":{"US":0,"CA":0,"RW":0}},"395416":{"name":"Excellence Club Junior Swim Up Suite Pool View","price":{"US":499,"CA":418,"RW":401}},"496624":{"name":"Excellence Club Junior Suite Pool View","price":{"US":467,"CA":391,"RW":376}},"568940":{"name":"Terrace Suite with Plunge Pool  ","price":{"US":478,"CA":401,"RW":386}}},"Adults 2":{"21123":{"name":"Excellence Club Honeymoon Suite Two-Story Rooftop Terrace W\/ Plunge Pool","price":{"US":0,"CA":0,"RW":0}},"21125":{"name":"Excellence Club Imperial Suite Two-Story Rooftop Terrace W\/ Plunge Pool","price":{"US":1146,"CA":962,"RW":924}},"100933":{"name":"Junior Suite Spa or Pool View","price":{"US":598,"CA":502,"RW":598}},"100935":{"name":"Junior Swim Up Suite Spa or Pool View","price":{"US":636,"CA":534,"RW":512}},"100937":{"name":"Two Story Rooftop Terrace Suite Spa or Pool View ","price":{"US":706,"CA":592,"RW":570}},"100940":{"name":"Excellence Club Junior Suite Ocean View","price":{"US":0,"CA":0,"RW":0}},"100944":{"name":"Excellence Club Two Story Rooftop Terrace Suite Ocean Front ","price":{"US":848,"CA":712,"RW":684}},"100946":{"name":"Excellence Club Honeymoon Suite W\/Private Pool","price":{"US":1020,"CA":856,"RW":822}},"100948":{"name":"Excellence Club Imperial Suite W\/Private Pool","price":{"US":0,"CA":0,"RW":0}},"395416":{"name":"Excellence Club Junior Swim Up Suite Pool View","price":{"US":730,"CA":612,"RW":588}},"496624":{"name":"Excellence Club Junior Suite Pool View","price":{"US":666,"CA":560,"RW":536}},"568940":{"name":"Terrace Suite with Plunge Pool  ","price":{"US":692,"CA":580,"RW":556}}},"Adults 3":{"100933":{"name":"Junior Suite Spa or Pool View","price":{"US":852,"CA":714,"RW":852}}}},"20190414":{"Adults 1":{"21123":{"name":"Excellence Club Honeymoon Suite Two-Story Rooftop Terrace W\/ Plunge Pool","price":{"US":0,"CA":0,"RW":0}},"21125":{"name":"Excellence Club Imperial Suite Two-Story Rooftop Terrace W\/ Plunge Pool","price":{"US":706,"CA":592,"RW":570}},"100933":{"name":"Junior Suite Spa or Pool View","price":{"US":432,"CA":362,"RW":348}},"100935":{"name":"Junior Swim Up Suite Spa or Pool View","price":{"US":451,"CA":378,"RW":363}},"100937":{"name":"Two Story Rooftop Terrace Suite Spa or Pool View ","price":{"US":486,"CA":408,"RW":392}},"100940":{"name":"Excellence Club Junior Suite Ocean View","price":{"US":0,"CA":0,"RW":0}},"100944":{"name":"Excellence Club Two Story Rooftop Terrace Suite Ocean Front ","price":{"US":557,"CA":467,"RW":449}},"100946":{"name":"Excellence Club Honeymoon Suite W\/Private Pool","price":{"US":643,"CA":539,"RW":519}},"100948":{"name":"Excellence Club Imperial Suite W\/Private Pool","price":{"US":0,"CA":0,"RW":0}},"395416":{"name":"Excellence Club Junior Swim Up Suite Pool View","price":{"US":499,"CA":418,"RW":401}},"496624":{"name":"Excellence Club Junior Suite Pool View","price":{"US":467,"CA":391,"RW":376}},"568940":{"name":"Terrace Suite with Plunge Pool  ","price":{"US":478,"CA":401,"RW":386}}},"Adults 2":{"21123":{"name":"Excellence Club Honeymoon Suite Two-Story Rooftop Terrace W\/ Plunge Pool","price":{"US":0,"CA":0,"RW":0}},"21125":{"name":"Excellence Club Imperial Suite Two-Story Rooftop Terrace W\/ Plunge Pool","price":{"US":1146,"CA":962,"RW":924}},"100933":{"name":"Junior Suite Spa or Pool View","price":{"US":598,"CA":502,"RW":482}},"100935":{"name":"Junior Swim Up Suite Spa or Pool View","price":{"US":636,"CA":534,"RW":512}},"100937":{"name":"Two Story Rooftop Terrace Suite Spa or Pool View ","price":{"US":706,"CA":592,"RW":570}},"100940":{"name":"Excellence Club Junior Suite Ocean View","price":{"US":0,"CA":0,"RW":0}},"100944":{"name":"Excellence Club Two Story Rooftop Terrace Suite Ocean Front ","price":{"US":848,"CA":712,"RW":684}},"100946":{"name":"Excellence Club Honeymoon Suite W\/Private Pool","price":{"US":1020,"CA":856,"RW":822}},"100948":{"name":"Excellence Club Imperial Suite W\/Private Pool","price":{"US":0,"CA":0,"RW":0}},"395416":{"name":"Excellence Club Junior Swim Up Suite Pool View","price":{"US":730,"CA":612,"RW":588}},"496624":{"name":"Excellence Club Junior Suite Pool View","price":{"US":666,"CA":560,"RW":536}},"568940":{"name":"Terrace Suite with Plunge Pool  ","price":{"US":692,"CA":580,"RW":556}}},"Adults 3":{"100933":{"name":"Junior Suite Spa or Pool View","price":{"US":852,"CA":714,"RW":684}}}},"20190415":{"Adults 1":{"21123":{"name":"Excellence Club Honeymoon Suite Two-Story Rooftop Terrace W\/ Plunge Pool","price":{"US":0,"CA":0,"RW":0}},"21125":{"name":"Excellence Club Imperial Suite Two-Story Rooftop Terrace W\/ Plunge Pool","price":{"US":0,"CA":0,"RW":0}},"100933":{"name":"Junior Suite Spa or Pool View","price":{"US":432,"CA":362,"RW":348}},"100935":{"name":"Junior Swim Up Suite Spa or Pool View","price":{"US":451,"CA":378,"RW":363}},"100937":{"name":"Two Story Rooftop Terrace Suite Spa or Pool View ","price":{"US":486,"CA":408,"RW":392}},"100940":{"name":"Excellence Club Junior Suite Ocean View","price":{"US":499,"CA":418,"RW":401}},"100944":{"name":"Excellence Club Two Story Rooftop Terrace Suite Ocean Front ","price":{"US":0,"CA":0,"RW":0}},"100946":{"name":"Excellence Club Honeymoon Suite W\/Private Pool","price":{"US":643,"CA":539,"RW":519}},"100948":{"name":"Excellence Club Imperial Suite W\/Private Pool","price":{"US":0,"CA":0,"RW":0}},"395416":{"name":"Excellence Club Junior Swim Up Suite Pool View","price":{"US":499,"CA":418,"RW":401}},"496624":{"name":"Excellence Club Junior Suite Pool View","price":{"US":467,"CA":391,"RW":376}},"568940":{"name":"Terrace Suite with Plunge Pool  ","price":{"US":478,"CA":401,"RW":386}}},"Adults 2":{"21123":{"name":"Excellence Club Honeymoon Suite Two-Story Rooftop Terrace W\/ Plunge Pool","price":{"US":0,"CA":0,"RW":0}},"21125":{"name":"Excellence Club Imperial Suite Two-Story Rooftop Terrace W\/ Plunge Pool","price":{"US":0,"CA":0,"RW":0}},"100933":{"name":"Junior Suite Spa or Pool View","price":{"US":598,"CA":502,"RW":482}},"100935":{"name":"Junior Swim Up Suite Spa or Pool View","price":{"US":636,"CA":534,"RW":512}},"100937":{"name":"Two Story Rooftop Terrace Suite Spa or Pool View ","price":{"US":706,"CA":592,"RW":570}},"100940":{"name":"Excellence Club Junior Suite Ocean View","price":{"US":730,"CA":612,"RW":588}},"100944":{"name":"Excellence Club Two Story Rooftop Terrace Suite Ocean Front ","price":{"US":0,"CA":0,"RW":0}},"100946":{"name":"Excellence Club Honeymoon Suite W\/Private Pool","price":{"US":1020,"CA":856,"RW":822}},"100948":{"name":"Excellence Club Imperial Suite W\/Private Pool","price":{"US":0,"CA":0,"RW":0}},"395416":{"name":"Excellence Club Junior Swim Up Suite Pool View","price":{"US":730,"CA":612,"RW":588}},"496624":{"name":"Excellence Club Junior Suite Pool View","price":{"US":666,"CA":560,"RW":536}},"568940":{"name":"Terrace Suite with Plunge Pool  ","price":{"US":692,"CA":580,"RW":556}}},"Adults 3":{"100933":{"name":"Junior Suite Spa or Pool View","price":{"US":852,"CA":714,"RW":684}}}},"20190416":{"Adults 1":{"21123":{"name":"Excellence Club Honeymoon Suite Two-Story Rooftop Terrace W\/ Plunge Pool","price":{"US":643,"CA":539,"RW":519}},"21125":{"name":"Excellence Club Imperial Suite Two-Story Rooftop Terrace W\/ Plunge Pool","price":{"US":0,"CA":0,"RW":0}},"100933":{"name":"Junior Suite Spa or Pool View","price":{"US":432,"CA":362,"RW":348}},"100935":{"name":"Junior Swim Up Suite Spa or Pool View","price":{"US":451,"CA":378,"RW":363}},"100937":{"name":"Two Story Rooftop Terrace Suite Spa or Pool View ","price":{"US":486,"CA":408,"RW":392}},"100940":{"name":"Excellence Club Junior Suite Ocean View","price":{"US":499,"CA":418,"RW":401}},"100944":{"name":"Excellence Club Two Story Rooftop Terrace Suite Ocean Front ","price":{"US":557,"CA":467,"RW":449}},"100946":{"name":"Excellence Club Honeymoon Suite W\/Private Pool","price":{"US":643,"CA":539,"RW":519}},"100948":{"name":"Excellence Club Imperial Suite W\/Private Pool","price":{"US":0,"CA":0,"RW":0}},"395416":{"name":"Excellence Club Junior Swim Up Suite Pool View","price":{"US":499,"CA":418,"RW":401}},"496624":{"name":"Excellence Club Junior Suite Pool View","price":{"US":467,"CA":391,"RW":376}},"568940":{"name":"Terrace Suite with Plunge Pool  ","price":{"US":478,"CA":401,"RW":386}}},"Adults 2":{"21123":{"name":"Excellence Club Honeymoon Suite Two-Story Rooftop Terrace W\/ Plunge Pool","price":{"US":1020,"CA":856,"RW":822}},"21125":{"name":"Excellence Club Imperial Suite Two-Story Rooftop Terrace W\/ Plunge Pool","price":{"US":0,"CA":0,"RW":0}},"100933":{"name":"Junior Suite Spa or Pool View","price":{"US":598,"CA":502,"RW":482}},"100935":{"name":"Junior Swim Up Suite Spa or Pool View","price":{"US":636,"CA":534,"RW":512}},"100937":{"name":"Two Story Rooftop Terrace Suite Spa or Pool View ","price":{"US":706,"CA":592,"RW":570}},"100940":{"name":"Excellence Club Junior Suite Ocean View","price":{"US":730,"CA":612,"RW":588}},"100944":{"name":"Excellence Club Two Story Rooftop Terrace Suite Ocean Front ","price":{"US":848,"CA":712,"RW":684}},"100946":{"name":"Excellence Club Honeymoon Suite W\/Private Pool","price":{"US":1020,"CA":856,"RW":822}},"100948":{"name":"Excellence Club Imperial Suite W\/Private Pool","price":{"US":0,"CA":0,"RW":0}},"395416":{"name":"Excellence Club Junior Swim Up Suite Pool View","price":{"US":730,"CA":612,"RW":588}},"496624":{"name":"Excellence Club Junior Suite Pool View","price":{"US":666,"CA":560,"RW":536}},"568940":{"name":"Terrace Suite with Plunge Pool  ","price":{"US":692,"CA":580,"RW":556}}},"Adults 3":{"100933":{"name":"Junior Suite Spa or Pool View","price":{"US":852,"CA":714,"RW":684}}}},"20190417":{"Adults 1":{"21123":{"name":"Excellence Club Honeymoon Suite Two-Story Rooftop Terrace W\/ Plunge Pool","price":{"US":643,"CA":539,"RW":519}},"21125":{"name":"Excellence Club Imperial Suite Two-Story Rooftop Terrace W\/ Plunge Pool","price":{"US":706,"CA":592,"RW":570}},"100933":{"name":"Junior Suite Spa or Pool View","price":{"US":432,"CA":362,"RW":348}},"100935":{"name":"Junior Swim Up Suite Spa or Pool View","price":{"US":451,"CA":378,"RW":363}},"100937":{"name":"Two Story Rooftop Terrace Suite Spa or Pool View ","price":{"US":486,"CA":408,"RW":392}},"100940":{"name":"Excellence Club Junior Suite Ocean View","price":{"US":499,"CA":418,"RW":401}},"100944":{"name":"Excellence Club Two Story Rooftop Terrace Suite Ocean Front ","price":{"US":0,"CA":0,"RW":0}},"100946":{"name":"Excellence Club Honeymoon Suite W\/Private Pool","price":{"US":0,"CA":0,"RW":0}},"100948":{"name":"Excellence Club Imperial Suite W\/Private Pool","price":{"US":0,"CA":0,"RW":0}},"395416":{"name":"Excellence Club Junior Swim Up Suite Pool View","price":{"US":499,"CA":418,"RW":401}},"496624":{"name":"Excellence Club Junior Suite Pool View","price":{"US":467,"CA":391,"RW":376}},"568940":{"name":"Terrace Suite with Plunge Pool  ","price":{"US":478,"CA":401,"RW":386}}},"Adults 2":{"21123":{"name":"Excellence Club Honeymoon Suite Two-Story Rooftop Terrace W\/ Plunge Pool","price":{"US":1020,"CA":856,"RW":822}},"21125":{"name":"Excellence Club Imperial Suite Two-Story Rooftop Terrace W\/ Plunge Pool","price":{"US":1146,"CA":962,"RW":924}},"100933":{"name":"Junior Suite Spa or Pool View","price":{"US":598,"CA":502,"RW":482}},"100935":{"name":"Junior Swim Up Suite Spa or Pool View","price":{"US":636,"CA":534,"RW":512}},"100937":{"name":"Two Story Rooftop Terrace Suite Spa or Pool View ","price":{"US":706,"CA":592,"RW":570}},"100940":{"name":"Excellence Club Junior Suite Ocean View","price":{"US":730,"CA":612,"RW":588}},"100944":{"name":"Excellence Club Two Story Rooftop Terrace Suite Ocean Front ","price":{"US":0,"CA":0,"RW":0}},"100946":{"name":"Excellence Club Honeymoon Suite W\/Private Pool","price":{"US":0,"CA":0,"RW":0}},"100948":{"name":"Excellence Club Imperial Suite W\/Private Pool","price":{"US":0,"CA":0,"RW":0}},"395416":{"name":"Excellence Club Junior Swim Up Suite Pool View","price":{"US":730,"CA":612,"RW":588}},"496624":{"name":"Excellence Club Junior Suite Pool View","price":{"US":666,"CA":560,"RW":536}},"568940":{"name":"Terrace Suite with Plunge Pool  ","price":{"US":692,"CA":580,"RW":556}}},"Adults 3":{"100933":{"name":"Junior Suite Spa or Pool View","price":{"US":852,"CA":714,"RW":684}}}},"20190418":{"Adults 1":{"21123":{"name":"Excellence Club Honeymoon Suite Two-Story Rooftop Terrace W\/ Plunge Pool","price":{"US":643,"CA":539,"RW":519}},"21125":{"name":"Excellence Club Imperial Suite Two-Story Rooftop Terrace W\/ Plunge Pool","price":{"US":0,"CA":0,"RW":0}},"100933":{"name":"Junior Suite Spa or Pool View","price":{"US":432,"CA":362,"RW":348}},"100935":{"name":"Junior Swim Up Suite Spa or Pool View","price":{"US":451,"CA":378,"RW":363}},"100937":{"name":"Two Story Rooftop Terrace Suite Spa or Pool View ","price":{"US":486,"CA":408,"RW":392}},"100940":{"name":"Excellence Club Junior Suite Ocean View","price":{"US":499,"CA":418,"RW":401}},"100944":{"name":"Excellence Club Two Story Rooftop Terrace Suite Ocean Front ","price":{"US":557,"CA":467,"RW":449}},"100946":{"name":"Excellence Club Honeymoon Suite W\/Private Pool","price":{"US":0,"CA":0,"RW":0}},"100948":{"name":"Excellence Club Imperial Suite W\/Private Pool","price":{"US":0,"CA":0,"RW":0}},"395416":{"name":"Excellence Club Junior Swim Up Suite Pool View","price":{"US":499,"CA":418,"RW":401}},"496624":{"name":"Excellence Club Junior Suite Pool View","price":{"US":467,"CA":391,"RW":376}},"568940":{"name":"Terrace Suite with Plunge Pool  ","price":{"US":478,"CA":401,"RW":386}}},"Adults 2":{"21123":{"name":"Excellence Club Honeymoon Suite Two-Story Rooftop Terrace W\/ Plunge Pool","price":{"US":1020,"CA":856,"RW":822}},"21125":{"name":"Excellence Club Imperial Suite Two-Story Rooftop Terrace W\/ Plunge Pool","price":{"US":0,"CA":0,"RW":0}},"100933":{"name":"Junior Suite Spa or Pool View","price":{"US":598,"CA":502,"RW":482}},"100935":{"name":"Junior Swim Up Suite Spa or Pool View","price":{"US":636,"CA":534,"RW":512}},"100937":{"name":"Two Story Rooftop Terrace Suite Spa or Pool View ","price":{"US":706,"CA":592,"RW":570}},"100940":{"name":"Excellence Club Junior Suite Ocean View","price":{"US":730,"CA":612,"RW":588}},"100944":{"name":"Excellence Club Two Story Rooftop Terrace Suite Ocean Front ","price":{"US":848,"CA":712,"RW":684}},"100946":{"name":"Excellence Club Honeymoon Suite W\/Private Pool","price":{"US":0,"CA":0,"RW":0}},"100948":{"name":"Excellence Club Imperial Suite W\/Private Pool","price":{"US":0,"CA":0,"RW":0}},"395416":{"name":"Excellence Club Junior Swim Up Suite Pool View","price":{"US":730,"CA":612,"RW":588}},"496624":{"name":"Excellence Club Junior Suite Pool View","price":{"US":666,"CA":560,"RW":536}},"568940":{"name":"Terrace Suite with Plunge Pool  ","price":{"US":692,"CA":580,"RW":556}}},"Adults 3":{"100933":{"name":"Junior Suite Spa or Pool View","price":{"US":852,"CA":714,"RW":684}}}},"20190419":{"Adults 1":{"21123":{"name":"Excellence Club Honeymoon Suite Two-Story Rooftop Terrace W\/ Plunge Pool","price":{"US":0,"CA":0,"RW":0}},"21125":{"name":"Excellence Club Imperial Suite Two-Story Rooftop Terrace W\/ Plunge Pool","price":{"US":0,"CA":0,"RW":0}},"100933":{"name":"Junior Suite Spa or Pool View","price":{"US":432,"CA":362,"RW":348}},"100935":{"name":"Junior Swim Up Suite Spa or Pool View","price":{"US":451,"CA":378,"RW":363}},"100937":{"name":"Two Story Rooftop Terrace Suite Spa or Pool View ","price":{"US":486,"CA":408,"RW":392}},"100940":{"name":"Excellence Club Junior Suite Ocean View","price":{"US":499,"CA":418,"RW":401}},"100944":{"name":"Excellence Club Two Story Rooftop Terrace Suite Ocean Front ","price":{"US":557,"CA":467,"RW":449}},"100946":{"name":"Excellence Club Honeymoon Suite W\/Private Pool","price":{"US":0,"CA":0,"RW":0}},"100948":{"name":"Excellence Club Imperial Suite W\/Private Pool","price":{"US":0,"CA":0,"RW":0}},"395416":{"name":"Excellence Club Junior Swim Up Suite Pool View","price":{"US":499,"CA":418,"RW":401}},"496624":{"name":"Excellence Club Junior Suite Pool View","price":{"US":467,"CA":391,"RW":376}},"568940":{"name":"Terrace Suite with Plunge Pool  ","price":{"US":478,"CA":401,"RW":386}}},"Adults 2":{"21123":{"name":"Excellence Club Honeymoon Suite Two-Story Rooftop Terrace W\/ Plunge Pool","price":{"US":0,"CA":0,"RW":0}},"21125":{"name":"Excellence Club Imperial Suite Two-Story Rooftop Terrace W\/ Plunge Pool","price":{"US":0,"CA":0,"RW":0}},"100933":{"name":"Junior Suite Spa or Pool View","price":{"US":598,"CA":502,"RW":482}},"100935":{"name":"Junior Swim Up Suite Spa or Pool View","price":{"US":636,"CA":534,"RW":512}},"100937":{"name":"Two Story Rooftop Terrace Suite Spa or Pool View ","price":{"US":706,"CA":592,"RW":570}},"100940":{"name":"Excellence Club Junior Suite Ocean View","price":{"US":730,"CA":612,"RW":588}},"100944":{"name":"Excellence Club Two Story Rooftop Terrace Suite Ocean Front ","price":{"US":848,"CA":712,"RW":684}},"100946":{"name":"Excellence Club Honeymoon Suite W\/Private Pool","price":{"US":0,"CA":0,"RW":0}},"100948":{"name":"Excellence Club Imperial Suite W\/Private Pool","price":{"US":0,"CA":0,"RW":0}},"395416":{"name":"Excellence Club Junior Swim Up Suite Pool View","price":{"US":730,"CA":612,"RW":588}},"496624":{"name":"Excellence Club Junior Suite Pool View","price":{"US":666,"CA":560,"RW":536}},"568940":{"name":"Terrace Suite with Plunge Pool  ","price":{"US":692,"CA":580,"RW":556}}},"Adults 3":{"100933":{"name":"Junior Suite Spa or Pool View","price":{"US":852,"CA":714,"RW":684}}}},"20190420":{"Adults 1":{"21123":{"name":"Excellence Club Honeymoon Suite Two-Story Rooftop Terrace W\/ Plunge Pool","price":{"US":0,"CA":0,"RW":0}},"21125":{"name":"Excellence Club Imperial Suite Two-Story Rooftop Terrace W\/ Plunge Pool","price":{"US":0,"CA":0,"RW":0}},"100933":{"name":"Junior Suite Spa or Pool View","price":{"US":432,"CA":362,"RW":348}},"100935":{"name":"Junior Swim Up Suite Spa or Pool View","price":{"US":451,"CA":378,"RW":363}},"100937":{"name":"Two Story Rooftop Terrace Suite Spa or Pool View ","price":{"US":486,"CA":408,"RW":392}},"100940":{"name":"Excellence Club Junior Suite Ocean View","price":{"US":499,"CA":418,"RW":401}},"100944":{"name":"Excellence Club Two Story Rooftop Terrace Suite Ocean Front ","price":{"US":0,"CA":0,"RW":0}},"100946":{"name":"Excellence Club Honeymoon Suite W\/Private Pool","price":{"US":0,"CA":0,"RW":0}},"100948":{"name":"Excellence Club Imperial Suite W\/Private Pool","price":{"US":0,"CA":0,"RW":0}},"395416":{"name":"Excellence Club Junior Swim Up Suite Pool View","price":{"US":499,"CA":418,"RW":401}},"496624":{"name":"Excellence Club Junior Suite Pool View","price":{"US":467,"CA":391,"RW":376}},"568940":{"name":"Terrace Suite with Plunge Pool  ","price":{"US":478,"CA":401,"RW":386}}},"Adults 2":{"21123":{"name":"Excellence Club Honeymoon Suite Two-Story Rooftop Terrace W\/ Plunge Pool","price":{"US":0,"CA":0,"RW":0}},"21125":{"name":"Excellence Club Imperial Suite Two-Story Rooftop Terrace W\/ Plunge Pool","price":{"US":0,"CA":0,"RW":0}},"100933":{"name":"Junior Suite Spa or Pool View","price":{"US":598,"CA":502,"RW":482}},"100935":{"name":"Junior Swim Up Suite Spa or Pool View","price":{"US":636,"CA":534,"RW":512}},"100937":{"name":"Two Story Rooftop Terrace Suite Spa or Pool View ","price":{"US":706,"CA":592,"RW":570}},"100940":{"name":"Excellence Club Junior Suite Ocean View","price":{"US":730,"CA":612,"RW":588}},"100944":{"name":"Excellence Club Two Story Rooftop Terrace Suite Ocean Front ","price":{"US":0,"CA":0,"RW":0}},"100946":{"name":"Excellence Club Honeymoon Suite W\/Private Pool","price":{"US":0,"CA":0,"RW":0}},"100948":{"name":"Excellence Club Imperial Suite W\/Private Pool","price":{"US":0,"CA":0,"RW":0}},"395416":{"name":"Excellence Club Junior Swim Up Suite Pool View","price":{"US":730,"CA":612,"RW":588}},"496624":{"name":"Excellence Club Junior Suite Pool View","price":{"US":666,"CA":560,"RW":536}},"568940":{"name":"Terrace Suite with Plunge Pool  ","price":{"US":692,"CA":580,"RW":556}}},"Adults 3":{"100933":{"name":"Junior Suite Spa or Pool View","price":{"US":852,"CA":714,"RW":684}}}},"20190421":{"Adults 1":{"21123":{"name":"Excellence Club Honeymoon Suite Two-Story Rooftop Terrace W\/ Plunge Pool","price":{"US":0,"CA":0,"RW":0}},"21125":{"name":"Excellence Club Imperial Suite Two-Story Rooftop Terrace W\/ Plunge Pool","price":{"US":0,"CA":0,"RW":0}},"100933":{"name":"Junior Suite Spa or Pool View","price":{"US":432,"CA":362,"RW":348}},"100935":{"name":"Junior Swim Up Suite Spa or Pool View","price":{"US":451,"CA":378,"RW":363}},"100937":{"name":"Two Story Rooftop Terrace Suite Spa or Pool View ","price":{"US":486,"CA":408,"RW":392}},"100940":{"name":"Excellence Club Junior Suite Ocean View","price":{"US":499,"CA":418,"RW":401}},"100944":{"name":"Excellence Club Two Story Rooftop Terrace Suite Ocean Front ","price":{"US":557,"CA":467,"RW":449}},"100946":{"name":"Excellence Club Honeymoon Suite W\/Private Pool","price":{"US":0,"CA":0,"RW":0}},"100948":{"name":"Excellence Club Imperial Suite W\/Private Pool","price":{"US":0,"CA":0,"RW":0}},"395416":{"name":"Excellence Club Junior Swim Up Suite Pool View","price":{"US":499,"CA":418,"RW":401}},"496624":{"name":"Excellence Club Junior Suite Pool View","price":{"US":467,"CA":391,"RW":376}},"568940":{"name":"Terrace Suite with Plunge Pool  ","price":{"US":478,"CA":401,"RW":386}}},"Adults 2":{"21123":{"name":"Excellence Club Honeymoon Suite Two-Story Rooftop Terrace W\/ Plunge Pool","price":{"US":0,"CA":0,"RW":0}},"21125":{"name":"Excellence Club Imperial Suite Two-Story Rooftop Terrace W\/ Plunge Pool","price":{"US":0,"CA":0,"RW":0}},"100933":{"name":"Junior Suite Spa or Pool View","price":{"US":598,"CA":502,"RW":482}},"100935":{"name":"Junior Swim Up Suite Spa or Pool View","price":{"US":636,"CA":534,"RW":512}},"100937":{"name":"Two Story Rooftop Terrace Suite Spa or Pool View ","price":{"US":706,"CA":592,"RW":570}},"100940":{"name":"Excellence Club Junior Suite Ocean View","price":{"US":730,"CA":612,"RW":588}},"100944":{"name":"Excellence Club Two Story Rooftop Terrace Suite Ocean Front ","price":{"US":848,"CA":712,"RW":684}},"100946":{"name":"Excellence Club Honeymoon Suite W\/Private Pool","price":{"US":0,"CA":0,"RW":0}},"100948":{"name":"Excellence Club Imperial Suite W\/Private Pool","price":{"US":0,"CA":0,"RW":0}},"395416":{"name":"Excellence Club Junior Swim Up Suite Pool View","price":{"US":730,"CA":612,"RW":588}},"496624":{"name":"Excellence Club Junior Suite Pool View","price":{"US":666,"CA":560,"RW":536}},"568940":{"name":"Terrace Suite with Plunge Pool  ","price":{"US":692,"CA":580,"RW":556}}},"Adults 3":{"100933":{"name":"Junior Suite Spa or Pool View","price":{"US":852,"CA":714,"RW":684}}}},"20190422":{"Adults 1":{"21123":{"name":"Excellence Club Honeymoon Suite Two-Story Rooftop Terrace W\/ Plunge Pool","price":{"US":0,"CA":0,"RW":0}},"21125":{"name":"Excellence Club Imperial Suite Two-Story Rooftop Terrace W\/ Plunge Pool","price":{"US":0,"CA":0,"RW":0}},"100933":{"name":"Junior Suite Spa or Pool View","price":{"US":432,"CA":362,"RW":348}},"100935":{"name":"Junior Swim Up Suite Spa or Pool View","price":{"US":451,"CA":378,"RW":363}},"100937":{"name":"Two Story Rooftop Terrace Suite Spa or Pool View ","price":{"US":486,"CA":408,"RW":392}},"100940":{"name":"Excellence Club Junior Suite Ocean View","price":{"US":499,"CA":418,"RW":401}},"100944":{"name":"Excellence Club Two Story Rooftop Terrace Suite Ocean Front ","price":{"US":557,"CA":467,"RW":449}},"100946":{"name":"Excellence Club Honeymoon Suite W\/Private Pool","price":{"US":643,"CA":539,"RW":519}},"100948":{"name":"Excellence Club Imperial Suite W\/Private Pool","price":{"US":0,"CA":0,"RW":0}},"395416":{"name":"Excellence Club Junior Swim Up Suite Pool View","price":{"US":499,"CA":418,"RW":401}},"496624":{"name":"Excellence Club Junior Suite Pool View","price":{"US":467,"CA":391,"RW":376}},"568940":{"name":"Terrace Suite with Plunge Pool  ","price":{"US":478,"CA":401,"RW":386}}},"Adults 2":{"21123":{"name":"Excellence Club Honeymoon Suite Two-Story Rooftop Terrace W\/ Plunge Pool","price":{"US":0,"CA":0,"RW":0}},"21125":{"name":"Excellence Club Imperial Suite Two-Story Rooftop Terrace W\/ Plunge Pool","price":{"US":0,"CA":0,"RW":0}},"100933":{"name":"Junior Suite Spa or Pool View","price":{"US":598,"CA":502,"RW":482}},"100935":{"name":"Junior Swim Up Suite Spa or Pool View","price":{"US":636,"CA":534,"RW":512}},"100937":{"name":"Two Story Rooftop Terrace Suite Spa or Pool View ","price":{"US":706,"CA":592,"RW":570}},"100940":{"name":"Excellence Club Junior Suite Ocean View","price":{"US":730,"CA":612,"RW":588}},"100944":{"name":"Excellence Club Two Story Rooftop Terrace Suite Ocean Front ","price":{"US":848,"CA":712,"RW":684}},"100946":{"name":"Excellence Club Honeymoon Suite W\/Private Pool","price":{"US":1020,"CA":856,"RW":822}},"100948":{"name":"Excellence Club Imperial Suite W\/Private Pool","price":{"US":0,"CA":0,"RW":0}},"395416":{"name":"Excellence Club Junior Swim Up Suite Pool View","price":{"US":730,"CA":612,"RW":588}},"496624":{"name":"Excellence Club Junior Suite Pool View","price":{"US":666,"CA":560,"RW":536}},"568940":{"name":"Terrace Suite with Plunge Pool  ","price":{"US":692,"CA":580,"RW":556}}},"Adults 3":{"100933":{"name":"Junior Suite Spa or Pool View","price":{"US":852,"CA":714,"RW":684}}}},"20190423":{"Adults 1":{"21123":{"name":"Excellence Club Honeymoon Suite Two-Story Rooftop Terrace W\/ Plunge Pool","price":{"US":0,"CA":0,"RW":0}},"21125":{"name":"Excellence Club Imperial Suite Two-Story Rooftop Terrace W\/ Plunge Pool","price":{"US":0,"CA":0,"RW":0}},"100933":{"name":"Junior Suite Spa or Pool View","price":{"US":432,"CA":362,"RW":348}},"100935":{"name":"Junior Swim Up Suite Spa or Pool View","price":{"US":451,"CA":378,"RW":363}},"100937":{"name":"Two Story Rooftop Terrace Suite Spa or Pool View ","price":{"US":486,"CA":408,"RW":392}},"100940":{"name":"Excellence Club Junior Suite Ocean View","price":{"US":499,"CA":418,"RW":401}},"100944":{"name":"Excellence Club Two Story Rooftop Terrace Suite Ocean Front ","price":{"US":557,"CA":467,"RW":449}},"100946":{"name":"Excellence Club Honeymoon Suite W\/Private Pool","price":{"US":643,"CA":539,"RW":519}},"100948":{"name":"Excellence Club Imperial Suite W\/Private Pool","price":{"US":0,"CA":0,"RW":0}},"395416":{"name":"Excellence Club Junior Swim Up Suite Pool View","price":{"US":499,"CA":418,"RW":401}},"496624":{"name":"Excellence Club Junior Suite Pool View","price":{"US":467,"CA":391,"RW":376}},"568940":{"name":"Terrace Suite with Plunge Pool  ","price":{"US":478,"CA":401,"RW":386}}},"Adults 2":{"21123":{"name":"Excellence Club Honeymoon Suite Two-Story Rooftop Terrace W\/ Plunge Pool","price":{"US":0,"CA":0,"RW":0}},"21125":{"name":"Excellence Club Imperial Suite Two-Story Rooftop Terrace W\/ Plunge Pool","price":{"US":0,"CA":0,"RW":0}},"100933":{"name":"Junior Suite Spa or Pool View","price":{"US":598,"CA":502,"RW":482}},"100935":{"name":"Junior Swim Up Suite Spa or Pool View","price":{"US":636,"CA":534,"RW":512}},"100937":{"name":"Two Story Rooftop Terrace Suite Spa or Pool View ","price":{"US":706,"CA":592,"RW":570}},"100940":{"name":"Excellence Club Junior Suite Ocean View","price":{"US":730,"CA":612,"RW":588}},"100944":{"name":"Excellence Club Two Story Rooftop Terrace Suite Ocean Front ","price":{"US":848,"CA":712,"RW":684}},"100946":{"name":"Excellence Club Honeymoon Suite W\/Private Pool","price":{"US":1020,"CA":856,"RW":822}},"100948":{"name":"Excellence Club Imperial Suite W\/Private Pool","price":{"US":0,"CA":0,"RW":0}},"395416":{"name":"Excellence Club Junior Swim Up Suite Pool View","price":{"US":730,"CA":612,"RW":588}},"496624":{"name":"Excellence Club Junior Suite Pool View","price":{"US":666,"CA":560,"RW":536}},"568940":{"name":"Terrace Suite with Plunge Pool  ","price":{"US":692,"CA":580,"RW":556}}},"Adults 3":{"100933":{"name":"Junior Suite Spa or Pool View","price":{"US":852,"CA":714,"RW":684}}}},"20190424":{"Adults 1":{"21123":{"name":"Excellence Club Honeymoon Suite Two-Story Rooftop Terrace W\/ Plunge Pool","price":{"US":0,"CA":0,"RW":0}},"21125":{"name":"Excellence Club Imperial Suite Two-Story Rooftop Terrace W\/ Plunge Pool","price":{"US":0,"CA":0,"RW":0}},"100933":{"name":"Junior Suite Spa or Pool View","price":{"US":432,"CA":362,"RW":348}},"100935":{"name":"Junior Swim Up Suite Spa or Pool View","price":{"US":451,"CA":378,"RW":363}},"100937":{"name":"Two Story Rooftop Terrace Suite Spa or Pool View ","price":{"US":486,"CA":408,"RW":392}},"100940":{"name":"Excellence Club Junior Suite Ocean View","price":{"US":499,"CA":418,"RW":401}},"100944":{"name":"Excellence Club Two Story Rooftop Terrace Suite Ocean Front ","price":{"US":557,"CA":467,"RW":449}},"100946":{"name":"Excellence Club Honeymoon Suite W\/Private Pool","price":{"US":0,"CA":0,"RW":0}},"100948":{"name":"Excellence Club Imperial Suite W\/Private Pool","price":{"US":0,"CA":0,"RW":0}},"395416":{"name":"Excellence Club Junior Swim Up Suite Pool View","price":{"US":499,"CA":418,"RW":401}},"496624":{"name":"Excellence Club Junior Suite Pool View","price":{"US":467,"CA":391,"RW":376}},"568940":{"name":"Terrace Suite with Plunge Pool  ","price":{"US":478,"CA":401,"RW":386}}},"Adults 2":{"21123":{"name":"Excellence Club Honeymoon Suite Two-Story Rooftop Terrace W\/ Plunge Pool","price":{"US":0,"CA":0,"RW":0}},"21125":{"name":"Excellence Club Imperial Suite Two-Story Rooftop Terrace W\/ Plunge Pool","price":{"US":0,"CA":0,"RW":0}},"100933":{"name":"Junior Suite Spa or Pool View","price":{"US":598,"CA":502,"RW":482}},"100935":{"name":"Junior Swim Up Suite Spa or Pool View","price":{"US":636,"CA":534,"RW":512}},"100937":{"name":"Two Story Rooftop Terrace Suite Spa or Pool View ","price":{"US":706,"CA":592,"RW":570}},"100940":{"name":"Excellence Club Junior Suite Ocean View","price":{"US":730,"CA":612,"RW":588}},"100944":{"name":"Excellence Club Two Story Rooftop Terrace Suite Ocean Front ","price":{"US":848,"CA":712,"RW":684}},"100946":{"name":"Excellence Club Honeymoon Suite W\/Private Pool","price":{"US":0,"CA":0,"RW":0}},"100948":{"name":"Excellence Club Imperial Suite W\/Private Pool","price":{"US":0,"CA":0,"RW":0}},"395416":{"name":"Excellence Club Junior Swim Up Suite Pool View","price":{"US":730,"CA":612,"RW":588}},"496624":{"name":"Excellence Club Junior Suite Pool View","price":{"US":666,"CA":560,"RW":536}},"568940":{"name":"Terrace Suite with Plunge Pool  ","price":{"US":692,"CA":580,"RW":556}}},"Adults 3":{"100933":{"name":"Junior Suite Spa or Pool View","price":{"US":852,"CA":714,"RW":684}}}},"20190425":{"Adults 1":{"21123":{"name":"Excellence Club Honeymoon Suite Two-Story Rooftop Terrace W\/ Plunge Pool","price":{"US":0,"CA":0,"RW":0}},"21125":{"name":"Excellence Club Imperial Suite Two-Story Rooftop Terrace W\/ Plunge Pool","price":{"US":0,"CA":0,"RW":0}},"100933":{"name":"Junior Suite Spa or Pool View","price":{"US":432,"CA":362,"RW":348}},"100935":{"name":"Junior Swim Up Suite Spa or Pool View","price":{"US":451,"CA":378,"RW":363}},"100937":{"name":"Two Story Rooftop Terrace Suite Spa or Pool View ","price":{"US":486,"CA":408,"RW":392}},"100940":{"name":"Excellence Club Junior Suite Ocean View","price":{"US":0,"CA":0,"RW":0}},"100944":{"name":"Excellence Club Two Story Rooftop Terrace Suite Ocean Front ","price":{"US":557,"CA":467,"RW":449}},"100946":{"name":"Excellence Club Honeymoon Suite W\/Private Pool","price":{"US":0,"CA":0,"RW":0}},"100948":{"name":"Excellence Club Imperial Suite W\/Private Pool","price":{"US":0,"CA":0,"RW":0}},"395416":{"name":"Excellence Club Junior Swim Up Suite Pool View","price":{"US":499,"CA":418,"RW":401}},"496624":{"name":"Excellence Club Junior Suite Pool View","price":{"US":0,"CA":0,"RW":0}},"568940":{"name":"Terrace Suite with Plunge Pool  ","price":{"US":478,"CA":401,"RW":386}}},"Adults 2":{"21123":{"name":"Excellence Club Honeymoon Suite Two-Story Rooftop Terrace W\/ Plunge Pool","price":{"US":0,"CA":0,"RW":0}},"21125":{"name":"Excellence Club Imperial Suite Two-Story Rooftop Terrace W\/ Plunge Pool","price":{"US":0,"CA":0,"RW":0}},"100933":{"name":"Junior Suite Spa or Pool View","price":{"US":598,"CA":502,"RW":482}},"100935":{"name":"Junior Swim Up Suite Spa or Pool View","price":{"US":636,"CA":534,"RW":512}},"100937":{"name":"Two Story Rooftop Terrace Suite Spa or Pool View ","price":{"US":706,"CA":592,"RW":570}},"100940":{"name":"Excellence Club Junior Suite Ocean View","price":{"US":0,"CA":0,"RW":0}},"100944":{"name":"Excellence Club Two Story Rooftop Terrace Suite Ocean Front ","price":{"US":848,"CA":712,"RW":684}},"100946":{"name":"Excellence Club Honeymoon Suite W\/Private Pool","price":{"US":0,"CA":0,"RW":0}},"100948":{"name":"Excellence Club Imperial Suite W\/Private Pool","price":{"US":0,"CA":0,"RW":0}},"395416":{"name":"Excellence Club Junior Swim Up Suite Pool View","price":{"US":730,"CA":612,"RW":588}},"496624":{"name":"Excellence Club Junior Suite Pool View","price":{"US":0,"CA":0,"RW":0}},"568940":{"name":"Terrace Suite with Plunge Pool  ","price":{"US":692,"CA":580,"RW":556}}},"Adults 3":{"100933":{"name":"Junior Suite Spa or Pool View","price":{"US":852,"CA":714,"RW":684}}}},"20190426":{"Adults 1":{"21123":{"name":"Excellence Club Honeymoon Suite Two-Story Rooftop Terrace W\/ Plunge Pool","price":{"US":0,"CA":0,"RW":0}},"21125":{"name":"Excellence Club Imperial Suite Two-Story Rooftop Terrace W\/ Plunge Pool","price":{"US":0,"CA":0,"RW":0}},"100933":{"name":"Junior Suite Spa or Pool View","price":{"US":432,"CA":362,"RW":348}},"100935":{"name":"Junior Swim Up Suite Spa or Pool View","price":{"US":451,"CA":378,"RW":363}},"100937":{"name":"Two Story Rooftop Terrace Suite Spa or Pool View ","price":{"US":486,"CA":408,"RW":392}},"100940":{"name":"Excellence Club Junior Suite Ocean View","price":{"US":0,"CA":0,"RW":0}},"100944":{"name":"Excellence Club Two Story Rooftop Terrace Suite Ocean Front ","price":{"US":0,"CA":0,"RW":0}},"100946":{"name":"Excellence Club Honeymoon Suite W\/Private Pool","price":{"US":0,"CA":0,"RW":0}},"100948":{"name":"Excellence Club Imperial Suite W\/Private Pool","price":{"US":0,"CA":0,"RW":0}},"395416":{"name":"Excellence Club Junior Swim Up Suite Pool View","price":{"US":499,"CA":418,"RW":401}},"496624":{"name":"Excellence Club Junior Suite Pool View","price":{"US":467,"CA":391,"RW":376}},"568940":{"name":"Terrace Suite with Plunge Pool  ","price":{"US":478,"CA":401,"RW":386}}},"Adults 2":{"21123":{"name":"Excellence Club Honeymoon Suite Two-Story Rooftop Terrace W\/ Plunge Pool","price":{"US":0,"CA":0,"RW":0}},"21125":{"name":"Excellence Club Imperial Suite Two-Story Rooftop Terrace W\/ Plunge Pool","price":{"US":0,"CA":0,"RW":0}},"100933":{"name":"Junior Suite Spa or Pool View","price":{"US":598,"CA":502,"RW":482}},"100935":{"name":"Junior Swim Up Suite Spa or Pool View","price":{"US":636,"CA":534,"RW":512}},"100937":{"name":"Two Story Rooftop Terrace Suite Spa or Pool View ","price":{"US":706,"CA":592,"RW":570}},"100940":{"name":"Excellence Club Junior Suite Ocean View","price":{"US":0,"CA":0,"RW":0}},"100944":{"name":"Excellence Club Two Story Rooftop Terrace Suite Ocean Front ","price":{"US":0,"CA":0,"RW":0}},"100946":{"name":"Excellence Club Honeymoon Suite W\/Private Pool","price":{"US":0,"CA":0,"RW":0}},"100948":{"name":"Excellence Club Imperial Suite W\/Private Pool","price":{"US":0,"CA":0,"RW":0}},"395416":{"name":"Excellence Club Junior Swim Up Suite Pool View","price":{"US":730,"CA":612,"RW":588}},"496624":{"name":"Excellence Club Junior Suite Pool View","price":{"US":666,"CA":560,"RW":536}},"568940":{"name":"Terrace Suite with Plunge Pool  ","price":{"US":692,"CA":580,"RW":556}}},"Adults 3":{"100933":{"name":"Junior Suite Spa or Pool View","price":{"US":852,"CA":714,"RW":684}}}},"20190427":{"Adults 1":{"21123":{"name":"Excellence Club Honeymoon Suite Two-Story Rooftop Terrace W\/ Plunge Pool","price":{"US":0,"CA":0,"RW":0}},"21125":{"name":"Excellence Club Imperial Suite Two-Story Rooftop Terrace W\/ Plunge Pool","price":{"US":0,"CA":0,"RW":0}},"100933":{"name":"Junior Suite Spa or Pool View","price":{"US":432,"CA":362,"RW":348}},"100935":{"name":"Junior Swim Up Suite Spa or Pool View","price":{"US":451,"CA":378,"RW":363}},"100937":{"name":"Two Story Rooftop Terrace Suite Spa or Pool View ","price":{"US":486,"CA":408,"RW":392}},"100940":{"name":"Excellence Club Junior Suite Ocean View","price":{"US":0,"CA":0,"RW":0}},"100944":{"name":"Excellence Club Two Story Rooftop Terrace Suite Ocean Front ","price":{"US":557,"CA":467,"RW":449}},"100946":{"name":"Excellence Club Honeymoon Suite W\/Private Pool","price":{"US":0,"CA":0,"RW":0}},"100948":{"name":"Excellence Club Imperial Suite W\/Private Pool","price":{"US":0,"CA":0,"RW":0}},"395416":{"name":"Excellence Club Junior Swim Up Suite Pool View","price":{"US":499,"CA":418,"RW":401}},"496624":{"name":"Excellence Club Junior Suite Pool View","price":{"US":0,"CA":0,"RW":0}},"568940":{"name":"Terrace Suite with Plunge Pool  ","price":{"US":478,"CA":401,"RW":386}}},"Adults 2":{"21123":{"name":"Excellence Club Honeymoon Suite Two-Story Rooftop Terrace W\/ Plunge Pool","price":{"US":0,"CA":0,"RW":0}},"21125":{"name":"Excellence Club Imperial Suite Two-Story Rooftop Terrace W\/ Plunge Pool","price":{"US":0,"CA":0,"RW":0}},"100933":{"name":"Junior Suite Spa or Pool View","price":{"US":598,"CA":502,"RW":482}},"100935":{"name":"Junior Swim Up Suite Spa or Pool View","price":{"US":636,"CA":534,"RW":512}},"100937":{"name":"Two Story Rooftop Terrace Suite Spa or Pool View ","price":{"US":706,"CA":592,"RW":570}},"100940":{"name":"Excellence Club Junior Suite Ocean View","price":{"US":0,"CA":0,"RW":0}},"100944":{"name":"Excellence Club Two Story Rooftop Terrace Suite Ocean Front ","price":{"US":848,"CA":712,"RW":684}},"100946":{"name":"Excellence Club Honeymoon Suite W\/Private Pool","price":{"US":0,"CA":0,"RW":0}},"100948":{"name":"Excellence Club Imperial Suite W\/Private Pool","price":{"US":0,"CA":0,"RW":0}},"395416":{"name":"Excellence Club Junior Swim Up Suite Pool View","price":{"US":730,"CA":612,"RW":588}},"496624":{"name":"Excellence Club Junior Suite Pool View","price":{"US":0,"CA":0,"RW":0}},"568940":{"name":"Terrace Suite with Plunge Pool  ","price":{"US":692,"CA":580,"RW":556}}},"Adults 3":{"100933":{"name":"Junior Suite Spa or Pool View","price":{"US":852,"CA":714,"RW":684}}}},"20190428":{"Adults 1":{"21123":{"name":"Excellence Club Honeymoon Suite Two-Story Rooftop Terrace W\/ Plunge Pool","price":{"US":0,"CA":0,"RW":0}},"21125":{"name":"Excellence Club Imperial Suite Two-Story Rooftop Terrace W\/ Plunge Pool","price":{"US":0,"CA":0,"RW":0}},"100933":{"name":"Junior Suite Spa or Pool View","price":{"US":432,"CA":362,"RW":348}},"100935":{"name":"Junior Swim Up Suite Spa or Pool View","price":{"US":451,"CA":378,"RW":363}},"100937":{"name":"Two Story Rooftop Terrace Suite Spa or Pool View ","price":{"US":486,"CA":408,"RW":392}},"100940":{"name":"Excellence Club Junior Suite Ocean View","price":{"US":0,"CA":0,"RW":0}},"100944":{"name":"Excellence Club Two Story Rooftop Terrace Suite Ocean Front ","price":{"US":0,"CA":0,"RW":0}},"100946":{"name":"Excellence Club Honeymoon Suite W\/Private Pool","price":{"US":0,"CA":0,"RW":0}},"100948":{"name":"Excellence Club Imperial Suite W\/Private Pool","price":{"US":0,"CA":0,"RW":0}},"395416":{"name":"Excellence Club Junior Swim Up Suite Pool View","price":{"US":0,"CA":0,"RW":0}},"496624":{"name":"Excellence Club Junior Suite Pool View","price":{"US":467,"CA":391,"RW":376}},"568940":{"name":"Terrace Suite with Plunge Pool  ","price":{"US":478,"CA":401,"RW":386}}},"Adults 2":{"21123":{"name":"Excellence Club Honeymoon Suite Two-Story Rooftop Terrace W\/ Plunge Pool","price":{"US":0,"CA":0,"RW":0}},"21125":{"name":"Excellence Club Imperial Suite Two-Story Rooftop Terrace W\/ Plunge Pool","price":{"US":0,"CA":0,"RW":0}},"100933":{"name":"Junior Suite Spa or Pool View","price":{"US":598,"CA":502,"RW":482}},"100935":{"name":"Junior Swim Up Suite Spa or Pool View","price":{"US":636,"CA":534,"RW":512}},"100937":{"name":"Two Story Rooftop Terrace Suite Spa or Pool View ","price":{"US":706,"CA":592,"RW":570}},"100940":{"name":"Excellence Club Junior Suite Ocean View","price":{"US":0,"CA":0,"RW":0}},"100944":{"name":"Excellence Club Two Story Rooftop Terrace Suite Ocean Front ","price":{"US":0,"CA":0,"RW":0}},"100946":{"name":"Excellence Club Honeymoon Suite W\/Private Pool","price":{"US":0,"CA":0,"RW":0}},"100948":{"name":"Excellence Club Imperial Suite W\/Private Pool","price":{"US":0,"CA":0,"RW":0}},"395416":{"name":"Excellence Club Junior Swim Up Suite Pool View","price":{"US":0,"CA":0,"RW":0}},"496624":{"name":"Excellence Club Junior Suite Pool View","price":{"US":666,"CA":560,"RW":536}},"568940":{"name":"Terrace Suite with Plunge Pool  ","price":{"US":692,"CA":580,"RW":556}}},"Adults 3":{"100933":{"name":"Junior Suite Spa or Pool View","price":{"US":852,"CA":714,"RW":684}}}},"20190429":{"Adults 1":{"21123":{"name":"Excellence Club Honeymoon Suite Two-Story Rooftop Terrace W\/ Plunge Pool","price":{"US":0,"CA":0,"RW":0}},"21125":{"name":"Excellence Club Imperial Suite Two-Story Rooftop Terrace W\/ Plunge Pool","price":{"US":706,"CA":592,"RW":570}},"100933":{"name":"Junior Suite Spa or Pool View","price":{"US":432,"CA":362,"RW":348}},"100935":{"name":"Junior Swim Up Suite Spa or Pool View","price":{"US":451,"CA":378,"RW":363}},"100937":{"name":"Two Story Rooftop Terrace Suite Spa or Pool View ","price":{"US":486,"CA":408,"RW":392}},"100940":{"name":"Excellence Club Junior Suite Ocean View","price":{"US":499,"CA":418,"RW":401}},"100944":{"name":"Excellence Club Two Story Rooftop Terrace Suite Ocean Front ","price":{"US":557,"CA":467,"RW":449}},"100946":{"name":"Excellence Club Honeymoon Suite W\/Private Pool","price":{"US":0,"CA":0,"RW":0}},"100948":{"name":"Excellence Club Imperial Suite W\/Private Pool","price":{"US":0,"CA":0,"RW":0}},"395416":{"name":"Excellence Club Junior Swim Up Suite Pool View","price":{"US":499,"CA":418,"RW":401}},"496624":{"name":"Excellence Club Junior Suite Pool View","price":{"US":467,"CA":391,"RW":376}},"568940":{"name":"Terrace Suite with Plunge Pool  ","price":{"US":478,"CA":401,"RW":386}}},"Adults 2":{"21123":{"name":"Excellence Club Honeymoon Suite Two-Story Rooftop Terrace W\/ Plunge Pool","price":{"US":0,"CA":0,"RW":0}},"21125":{"name":"Excellence Club Imperial Suite Two-Story Rooftop Terrace W\/ Plunge Pool","price":{"US":1146,"CA":962,"RW":924}},"100933":{"name":"Junior Suite Spa or Pool View","price":{"US":598,"CA":502,"RW":482}},"100935":{"name":"Junior Swim Up Suite Spa or Pool View","price":{"US":636,"CA":534,"RW":512}},"100937":{"name":"Two Story Rooftop Terrace Suite Spa or Pool View ","price":{"US":706,"CA":592,"RW":570}},"100940":{"name":"Excellence Club Junior Suite Ocean View","price":{"US":730,"CA":612,"RW":588}},"100944":{"name":"Excellence Club Two Story Rooftop Terrace Suite Ocean Front ","price":{"US":848,"CA":712,"RW":684}},"100946":{"name":"Excellence Club Honeymoon Suite W\/Private Pool","price":{"US":0,"CA":0,"RW":0}},"100948":{"name":"Excellence Club Imperial Suite W\/Private Pool","price":{"US":0,"CA":0,"RW":0}},"395416":{"name":"Excellence Club Junior Swim Up Suite Pool View","price":{"US":730,"CA":612,"RW":588}},"496624":{"name":"Excellence Club Junior Suite Pool View","price":{"US":666,"CA":560,"RW":536}},"568940":{"name":"Terrace Suite with Plunge Pool  ","price":{"US":692,"CA":580,"RW":556}}},"Adults 3":{"100933":{"name":"Junior Suite Spa or Pool View","price":{"US":852,"CA":714,"RW":684}}}},"20190430":{"Adults 1":{"21123":{"name":"Excellence Club Honeymoon Suite Two-Story Rooftop Terrace W\/ Plunge Pool","price":{"US":0,"CA":0,"RW":0}},"21125":{"name":"Excellence Club Imperial Suite Two-Story Rooftop Terrace W\/ Plunge Pool","price":{"US":0,"CA":0,"RW":0}},"100933":{"name":"Junior Suite Spa or Pool View","price":{"US":432,"CA":362,"RW":348}},"100935":{"name":"Junior Swim Up Suite Spa or Pool View","price":{"US":451,"CA":378,"RW":363}},"100937":{"name":"Two Story Rooftop Terrace Suite Spa or Pool View ","price":{"US":486,"CA":408,"RW":392}},"100940":{"name":"Excellence Club Junior Suite Ocean View","price":{"US":499,"CA":418,"RW":401}},"100944":{"name":"Excellence Club Two Story Rooftop Terrace Suite Ocean Front ","price":{"US":557,"CA":467,"RW":449}},"100946":{"name":"Excellence Club Honeymoon Suite W\/Private Pool","price":{"US":0,"CA":0,"RW":0}},"100948":{"name":"Excellence Club Imperial Suite W\/Private Pool","price":{"US":0,"CA":0,"RW":0}},"395416":{"name":"Excellence Club Junior Swim Up Suite Pool View","price":{"US":499,"CA":418,"RW":401}},"496624":{"name":"Excellence Club Junior Suite Pool View","price":{"US":467,"CA":391,"RW":376}},"568940":{"name":"Terrace Suite with Plunge Pool  ","price":{"US":478,"CA":401,"RW":386}}},"Adults 2":{"21123":{"name":"Excellence Club Honeymoon Suite Two-Story Rooftop Terrace W\/ Plunge Pool","price":{"US":0,"CA":0,"RW":0}},"21125":{"name":"Excellence Club Imperial Suite Two-Story Rooftop Terrace W\/ Plunge Pool","price":{"US":0,"CA":0,"RW":0}},"100933":{"name":"Junior Suite Spa or Pool View","price":{"US":598,"CA":502,"RW":482}},"100935":{"name":"Junior Swim Up Suite Spa or Pool View","price":{"US":636,"CA":534,"RW":512}},"100937":{"name":"Two Story Rooftop Terrace Suite Spa or Pool View ","price":{"US":706,"CA":592,"RW":570}},"100940":{"name":"Excellence Club Junior Suite Ocean View","price":{"US":730,"CA":612,"RW":588}},"100944":{"name":"Excellence Club Two Story Rooftop Terrace Suite Ocean Front ","price":{"US":848,"CA":712,"RW":684}},"100946":{"name":"Excellence Club Honeymoon Suite W\/Private Pool","price":{"US":0,"CA":0,"RW":0}},"100948":{"name":"Excellence Club Imperial Suite W\/Private Pool","price":{"US":0,"CA":0,"RW":0}},"395416":{"name":"Excellence Club Junior Swim Up Suite Pool View","price":{"US":730,"CA":612,"RW":588}},"496624":{"name":"Excellence Club Junior Suite Pool View","price":{"US":666,"CA":560,"RW":536}},"568940":{"name":"Terrace Suite with Plunge Pool  ","price":{"US":692,"CA":580,"RW":556}}},"Adults 3":{"100933":{"name":"Junior Suite Spa or Pool View","price":{"US":852,"CA":714,"RW":684}}}}}}